apt2sbom/__init__.py
apt2sbom/apt2sbom.py
apt2sbom/dp2cdx.py
apt2sbom/dp2json.py
apt2sbom/dp2yaml.py
apt2sbom/piplist.py
apt2sbom/readconf.py
apt2sbom/wsbom.py
apt2sbom-0.9.6.dist-info/LICENSE.txt
apt2sbom-0.9.6.dist-info/METADATA
apt2sbom-0.9.6.dist-info/WHEEL
apt2sbom-0.9.6.dist-info/entry_points.txt
apt2sbom-0.9.6.dist-info/top_level.txt
apt2sbom-0.9.6.dist-info/RECORD
