Metadata-Version: 2.1
Name: apt2sbom
Version: 0.9.6
Summary: Convert APT information from Ubuntu into SBOM
Home-page: https://github.com/sbomtools/apt2sbom
Author: Eliot Lear
Author-email: lear@cisco.com
License: BSD 3-Clause License
Platform: UNKNOWN
License-File: LICENSE.txt
Requires-Dist: werkzeug
Requires-Dist: flask
Requires-Dist: flask-httpauth
Requires-Dist: pip-api
